<?xml version="1.0" encoding="utf-8" ?>
<elements>
	<info>
		<name>Feats</name>
		<description>Feats from Plane Shift: Ixalan.</description>
		<author url="https://media.wizards.com/2018/downloads/magic/plane-shift_ixalan.pdf">Wizards of the Coast</author>
		<update version="0.0.2">
			<file name="feats-ixalan.xml" url="https://raw.githubusercontent.com/aurorabuilder/elements/master/unearthed-arcana/planeshift/ixalan/feats-ixalan.xml" />
		</update>
	</info>
    <element name="Vampire Exultation" type="Feat" source="Plane Shift: Ixalan" id="ID_WOTC_PSI_FEAT_VAMPIRE_EXULTATION">
        <prerequisite>Ixalan Vampire</prerequisite>
        <requirements>ID_WOTC_PSI_VAMPIRE_SUBRACE_IXALAN</requirements>
        <description>
            <p><i>Prerequisite: Ixalan Vampire</i></p>
            <p>As an action, you can transform the lower half of your body into an inky black vapor, allowing you to float through the air. While transformed, you have a flying speed of 30 feet. You can maintain this form for up to 10 minutes. Once you use this ability, you can’t use it again until you finish a short or long rest.</p>
        </description>
        <sheet>
            <description>Once per rest you can gain a flying speed of 30 ft for 10 minutes.</description>
        </sheet>
    </element>
</elements>
